{"base":{"base64":"WTYW3hUzDA+y1V5VQQv5lA==","id":0},"node_modules_@babel_runtime_helpers_interopRequireDefault":{"base64":"Rrhxwmcbe1XiK1yJCgQOfA==","id":1},"node_modules_@babel_runtime_helpers_interopRequireWildcard":{"base64":"EA6oRRNo+4iEfLXhznMzPA==","id":2},"node_modules_@babel_runtime_helpers_typeof":{"base64":"swkESDyXFA+l/+oHu/zHPQ==","id":3},"node_modules_react_index":{"base64":"eCpcPXnmFyDIPuo5osaCbw==","id":4},"node_modules_react_cjs_react.production.min":{"base64":"9Nfw6A+5TGOBdEyMmUZ3ag==","id":5},"node_modules_object-assign_index":{"base64":"gPzhiGwlUJIwAVozKp6pMA==","id":6},"node_modules_@babel_runtime_helpers_extends":{"base64":"crQZmfMtwO/xP7FLgsZI6w==","id":7},"react-native-implementation":{"base64":"y9frW0uhN68fAhMqFB2DeQ==","id":8},"node_modules_fbjs_lib_invariant":{"base64":"9wgQz+Ksx0VbbbB9Z87+8Q==","id":9},"AccessibilityInfo.android":{"base64":"u27fvmgxxPmxgHMAx39lJQ==","id":10},"NativeModules":{"base64":"Xghr1BvA41+3TD/eTKf7EQ==","id":11},"node_modules_@babel_runtime_helpers_objectWithoutProperties":{"base64":"tbbuhcP+bXR40DOxJLK7NA==","id":12},"node_modules_@babel_runtime_helpers_objectWithoutPropertiesLoose":{"base64":"8wRP7ncRpuPehdL/KXdDXA==","id":13},"node_modules_@babel_runtime_helpers_slicedToArray":{"base64":"O74BsLhk4CMFGdf7Eiah2g==","id":14},"node_modules_@babel_runtime_helpers_arrayWithHoles":{"base64":"td9Rslxj6qWedNCHBlEhlw==","id":15},"node_modules_@babel_runtime_helpers_iterableToArrayLimit":{"base64":"8wjKK+Xafe4Ew/IVXiVqWQ==","id":16},"node_modules_@babel_runtime_helpers_unsupportedIterableToArray":{"base64":"kCzgmJPyAGlLwWdWmqMQxw==","id":17},"node_modules_@babel_runtime_helpers_arrayLikeToArray":{"base64":"SbtIYGCWxLCaiZqr3PHYFg==","id":18},"node_modules_@babel_runtime_helpers_nonIterableRest":{"base64":"CEJ2mUVWun4UCCZYIeupTQ==","id":19},"BatchedBridge":{"base64":"32V7kpbMx0dUyjWzp0dIyg==","id":20},"MessageQueue":{"base64":"4jZkXszsDqZkEwgoYU3SyA==","id":21},"node_modules_@babel_runtime_helpers_toConsumableArray":{"base64":"ZwRsV42pnTFTl1+S4ZhDgw==","id":22},"node_modules_@babel_runtime_helpers_arrayWithoutHoles":{"base64":"plVc4U8miXmF5WyDvADQiw==","id":23},"node_modules_@babel_runtime_helpers_iterableToArray":{"base64":"nrsyHA5WT/zlBZDLsIrMag==","id":24},"node_modules_@babel_runtime_helpers_nonIterableSpread":{"base64":"Zvr7PZMY9WoFkga9/s5tXQ==","id":25},"node_modules_@babel_runtime_helpers_classCallCheck":{"base64":"Xjt+YZ+b//3odThOlTYOcg==","id":26},"node_modules_@babel_runtime_helpers_createClass":{"base64":"+DtlPNMQ+js5ten1dsMf4w==","id":27},"ErrorUtils":{"base64":"TSnqZ1ZmWlOqTk4licyhDw==","id":28},"Systrace":{"base64":"eV0b7H4KAxT1ezsCQAjZhA==","id":29},"deepFreezeAndThrowOnMutationInDev":{"base64":"2/zTfYTRejcnyTC2Cvanbg==","id":30},"stringifySafe":{"base64":"XQL5bj2AwrXfFHjJ0E/4GQ==","id":31},"defineLazyObjectProperty":{"base64":"DI0z8Tw2j7Ues/n/2W7O4A==","id":32},"RCTDeviceEventEmitter":{"base64":"D/LiMtE4OVj1Ub0cetQE2A==","id":33},"node_modules_@babel_runtime_helpers_get":{"base64":"BdFXtRFi+sOoQ/NhbXQ/nw==","id":34},"node_modules_@babel_runtime_helpers_superPropBase":{"base64":"Jz0HOBajSCV5gfN6+78JSg==","id":35},"node_modules_@babel_runtime_helpers_getPrototypeOf":{"base64":"wIi5nB4wiCYrXk5FIqST8Q==","id":36},"node_modules_@babel_runtime_helpers_inherits":{"base64":"LRs7ztCRhD1v1HrG9PGW3Q==","id":37},"node_modules_@babel_runtime_helpers_setPrototypeOf":{"base64":"/f355eKcO2fzFDZ05/+6UA==","id":38},"node_modules_@babel_runtime_helpers_possibleConstructorReturn":{"base64":"zWQYPd/U6aS5AwobwHBphw==","id":39},"node_modules_@babel_runtime_helpers_assertThisInitialized":{"base64":"cLiPhK/8HgqOL3a3oliE7Q==","id":40},"EventEmitter":{"base64":"HNvjRzXkiOJFG2x1tsDwAA==","id":41},"EmitterSubscription":{"base64":"O+0UXDpTJCHOE3Zmo4kTeA==","id":42},"EventSubscription":{"base64":"7IZG8uLqpDpA95f7cPGTGA==","id":43},"EventSubscriptionVendor":{"base64":"OS5d/5qWcMInnTAE5vZxaA==","id":44},"node_modules_fbjs_lib_emptyFunction":{"base64":"P4jTNh7VmCcFkuSMlHeDFg==","id":45},"UIManager":{"base64":"X1LvY6CWusvNy1DuZdAqKA==","id":46},"Platform.android":{"base64":"TOdydo/4/IicY5lS8QvWvw==","id":47},"ActivityIndicator":{"base64":"CPkXEIVX3akSTIOOdvhflQ==","id":48},"node_modules_@babel_runtime_helpers_defineProperty":{"base64":"vkdEq9IsKKsd+hrMaIisPA==","id":49},"React":{"base64":"UM4tpjvqamGOdXj6UGkAQA==","id":50},"StyleSheet":{"base64":"lLtRs9A2tvC+qxniLnEqow==","id":51},"PixelRatio":{"base64":"ddizsH9b6tRQnwhkuzYWnw==","id":52},"Dimensions":{"base64":"9IQ8HHl6vxolbIgCts2fUQ==","id":53},"DeviceInfo":{"base64":"inT2xVnDb/eOiF91kxp88g==","id":54},"ReactNativeStyleAttributes":{"base64":"zw3OKnBBTMwLN0PTUPvcwg==","id":55},"ImageStylePropTypes":{"base64":"clMFzefoNTqLLfJqaBqGKQ==","id":56},"ColorPropType":{"base64":"l0+M6L6zXq44pedxiRZghA==","id":57},"normalizeColor":{"base64":"fc1R2+Ewr8nLaBe8zrrXqA==","id":58},"ImageResizeMode":{"base64":"8VO2bwbSBL8JOHd9X6DW8A==","id":59},"node_modules_fbjs_lib_keyMirror":{"base64":"GUgZSL1T7Dus97UOQTS3Ww==","id":60},"LayoutPropTypes":{"base64":"VvISeqMx7TKHLG2kYfXmGg==","id":61},"node_modules_prop-types_index":{"base64":"Bws+6QH5dNtKFo1LAox5jQ==","id":62},"node_modules_prop-types_factoryWithThrowingShims":{"base64":"Mg4cLRMVyzC8JX/F08BT2A==","id":63},"node_modules_prop-types_lib_ReactPropTypesSecret":{"base64":"Y7HAes0tJwm3NBZZXZSCng==","id":64},"ShadowPropTypesIOS":{"base64":"85UVkkzUHpUCntD8kObYmg==","id":65},"TransformPropTypes":{"base64":"lGqdvqD+pRns/eWftBbaRA==","id":66},"deprecatedPropType":{"base64":"Yu91yjr3R1h5yzxfrmZyBg==","id":67},"TextStylePropTypes":{"base64":"d8vq6WqtRh9Id327iQAxnA==","id":68},"ViewStylePropTypes":{"base64":"rnhnQIt76E1hnqo3UBsGvQ==","id":69},"processColor":{"base64":"RlH56Hcuxf6MoVLL9S2+gw==","id":70},"processTransform":{"base64":"WHJ47KcUrR7V6jmcAsgG8Q==","id":71},"MatrixMath":{"base64":"0RIYUZJ8/TK8Na8OR7ckyg==","id":72},"sizesDiffer":{"base64":"U3HXv6ldvBIWvoKwFgd5mA==","id":73},"StyleSheetValidation":{"base64":"xK3tSA5Lz00Wghnbfben5w==","id":74},"flattenStyle":{"base64":"zD4tR9zUgSob7v2DP/ew2A==","id":75},"View":{"base64":"Q1HP6+S2HYql76HQIHEABQ==","id":76},"TextAncestor":{"base64":"BfOFGkUh/+DqQLh4jihIgA==","id":77},"ViewNativeComponent":{"base64":"qAdWmbVdr4biPJN1y0yD4Q==","id":78},"ReactNative":{"base64":"c7+DU5hQ2aGMfPIZkPbVTw==","id":79},"ReactNativeRenderer-prod":{"base64":"WV73KJROys1WKb8dzgOuPA==","id":80},"InitializeCore":{"base64":"D7CYBu8otOKaphzgPoVGWA==","id":81},"PolyfillFunctions":{"base64":"HW3gxzJYyeZcJTRjKcv7Kg==","id":82},"_shouldPolyfillES6Collection":{"base64":"U5SjRoK77kg0obRH8z2LFw==","id":83},"Map":{"base64":"RvPqBWyqMSa5Hz9wvuoGjA==","id":84},"guid":{"base64":"HgylsSUvH2seCskb5+chng==","id":85},"node_modules_fbjs_lib_isNode":{"base64":"iapmr66NIUtBJIijRtzBtA==","id":86},"toIterator":{"base64":"/5z98+BU2M6mcGPfqCbQIQ==","id":87},"Set":{"base64":"XVt4aZ5XEE8voDu997kZew==","id":88},"ExceptionsManager":{"base64":"JD3CzHdGmc//fthC3z1diA==","id":89},"parseErrorStack":{"base64":"YVus+SnH6NNiF8+1gO4g8w==","id":90},"node_modules_stacktrace-parser_dist_stack-trace-parser.cjs":{"base64":"VYbnUfyZ4FYfuN79VPyvBQ==","id":91},"ReactNativeVersionCheck":{"base64":"Thin4CimXBTeKuAYycUgmw==","id":92},"ReactNativeVersion":{"base64":"tXf/T4QsYrihIs65nClqYA==","id":93},"Promise":{"base64":"paPw8oekSJgqrFIM/+R3mg==","id":94},"node_modules_fbjs_lib_Promise.native":{"base64":"uu4L8ROXiyTBO5Le24ra1w==","id":95},"node_modules_promise_setimmediate_es6-extensions":{"base64":"GF12nnh1yEh4Auzelp3beg==","id":96},"node_modules_promise_setimmediate_core":{"base64":"aqiADUTFINeTkcHkV5rvGg==","id":97},"node_modules_promise_setimmediate_done":{"base64":"WpA6aHFS9bwOfP9/DiVoFQ==","id":98},"node_modules_regenerator-runtime_runtime":{"base64":"OBLO0xcV858djAv+aXBqzg==","id":99},"JSTimers":{"base64":"meUPPmaEYylVf6xUjGZtOQ==","id":100},"node_modules_fbjs_lib_performanceNow":{"base64":"qW4hI8FSvXGmOYCMW/sw4g==","id":101},"node_modules_fbjs_lib_performance":{"base64":"lbmsRCWKcQsdpS+SoX82ug==","id":102},"node_modules_fbjs_lib_ExecutionEnvironment":{"base64":"chBuYAGnAd1gjTs4Pt9lwA==","id":103},"node_modules_fbjs_lib_warning":{"base64":"f9D+XAhquedChCFGuVQdqQ==","id":104},"XMLHttpRequest":{"base64":"YlP1hRVcF8LuQkI0zh80lA==","id":105},"node_modules_event-target-shim_lib_event-target":{"base64":"7OoRrwU7ZWOoWIXwPPWRfw==","id":106},"node_modules_event-target-shim_lib_commons":{"base64":"LZyCWPhWCd2wECaP7oy3AA==","id":107},"node_modules_event-target-shim_lib_custom-event-target":{"base64":"SheNCeBs52vkZhUMVq5/Rw==","id":108},"node_modules_event-target-shim_lib_event-wrapper":{"base64":"APwn3QmCEzbpMNr+QMmCTA==","id":109},"RCTNetworking.android":{"base64":"0V5sEuSE+0va/cD5VuxZmA==","id":110},"MissingNativeEventEmitterShim":{"base64":"EYKJp9T+fL/Y11LKYZMLcg==","id":111},"NativeEventEmitter":{"base64":"lJCg5ib9aUuGJLQ4B7zQqA==","id":112},"convertRequestBody":{"base64":"ugxednNVjVMnA4cd/w6DBw==","id":113},"binaryToBase64":{"base64":"025dJlf+qoVJYp8J5lvheA==","id":114},"node_modules_base64-js_index":{"base64":"Pj1VZFnYXRph403MM7xu/g==","id":115},"Blob":{"base64":"6AFsha2ji9xfrGFuwTGARw==","id":116},"BlobManager":{"base64":"ygbTOoxPrbDjcDZFGkVXVw==","id":117},"BlobRegistry":{"base64":"NwiIOKupyWwiv8J0giMo4g==","id":118},"FormData":{"base64":"kI0HU64pntR3FS1zGvZBdw==","id":119},"fetch":{"base64":"U3QDSkDI1oAMtPRJwuoAoA==","id":120},"whatwg-fetch":{"base64":"a7Xy9K7IGAWs/+78HOQ77w==","id":121},"WebSocket":{"base64":"Re3BuWQH2dIT3RE1lioyoA==","id":122},"WebSocketEvent":{"base64":"ThQ6r+o3BGbu3mP2LvTRog==","id":123},"File":{"base64":"CyeRgpD/UyO+oeO3ipzwTg==","id":124},"FileReader":{"base64":"NQpuJrnKBNOONgwWD8pyCw==","id":125},"URL":{"base64":"5rORqNLE1FkCojqLZYVwPQ==","id":126},"Alert":{"base64":"uSBx1hyISYFxkodFylMHiw==","id":127},"AlertIOS":{"base64":"fMDFV5crsb+fKNICxvKBRA==","id":128},"Geolocation":{"base64":"Mj1OtwslKstKBOr54Igllw==","id":129},"node_modules_@babel_runtime_regenerator_index":{"base64":"csrX55L+MRhAJRvu3rhS9A==","id":130},"node_modules_@babel_runtime_node_modules_regenerator-runtime_runtime":{"base64":"AHs2wJ6YsxTSlZvyWa/ZYQ==","id":131},"logError":{"base64":"h+ca48rkiZmlQBKrNrCb7Q==","id":132},"PermissionsAndroid":{"base64":"tFJxpNpzaSZLLCUhimGRJQ==","id":133},"HeapCapture":{"base64":"QdWxUXlLIYAG+GIT5iMFng==","id":134},"SamplingProfiler":{"base64":"6+0RkBSrYzL39JigFTOXlg==","id":135},"RCTLog":{"base64":"rfJoPfeCdJuEngNDCsZ6Qg==","id":136},"RCTNativeAppEventEmitter":{"base64":"6xEQ5S4Lkrj2RqA/pK85bA==","id":137},"PerformanceLogger":{"base64":"LQQlqpKCV+T0dCWoYWdhyQ==","id":138},"infoLog":{"base64":"ta2n5GuDPncL8Ufdtu3YEw==","id":139},"JSDevSupportModule":{"base64":"9QFOoLT38ZdF1GdjNkhdfw==","id":140},"ReactNativeViewConfigRegistry":{"base64":"hoPyS6YnN6ieyXhOKOfYxg==","id":141},"RCTEventEmitter":{"base64":"UsFnDOcS40Iz/tPv8TNVkw==","id":142},"deepDiffer":{"base64":"8ciUu+ybY1v5teB8qfLM7Q==","id":143},"TextInputState":{"base64":"Igw6m1+Ga3jLmDb7sVSNbw==","id":144},"node_modules_scheduler_index":{"base64":"E+xUusAWoF3JiAS4U9nLpA==","id":145},"node_modules_scheduler_cjs_scheduler.production.min":{"base64":"GQmNZAY1BLuduLZwiqM/yw==","id":146},"requireNativeComponent":{"base64":"Mb9vVz6FB7M4KwrZRK3Yuw==","id":147},"createReactNativeComponentClass":{"base64":"4xWo7SqVRhUk+kWa+ShvxQ==","id":148},"getNativeComponentAttributes":{"base64":"2kgHagMLEWA9ag5eEmUjvw==","id":149},"insetsDiffer":{"base64":"ujFjpp0ObPF7X0V8NTbiUw==","id":150},"matricesDiffer":{"base64":"0+hXEJIY1O0zbglJn+4KGQ==","id":151},"pointsDiffer":{"base64":"fXeJr19fi+/rLIvrBNXUiQ==","id":152},"resolveAssetSource":{"base64":"XN+/erZPz8KTjADvd7tG3A==","id":153},"AssetRegistry":{"base64":"VyxI89ulsVvgVwVEK4/I4Q==","id":154},"AssetSourceResolver":{"base64":"XbHxmud/9C6OvQuMJBLNfg==","id":155},"node_modules_react-native_local-cli_bundle_assetPathUtils":{"base64":"9DmoM85U0dSVbgfrRgtNEQ==","id":156},"ProgressBarAndroid.android":{"base64":"znGyfUHIqoD7jlV43BcQ9A==","id":157},"ReactNativeART":{"base64":"uKJ4UV8Lh06YOCuHTOTk6Q==","id":158},"node_modules_art_core_color":{"base64":"8vEdIV2+tH2+Ri24jM/CCA==","id":159},"ARTSerializablePath":{"base64":"7er45WOSSwaF/BkKqL/rvQ==","id":160},"node_modules_art_core_class":{"base64":"Be60afr38do55xLZlVrWxQ==","id":161},"node_modules_art_core_path":{"base64":"tIaTI0iIYGpt0jZikfDOBw==","id":162},"node_modules_art_core_transform":{"base64":"IgceMPcsmaEirPaXey2S8w==","id":163},"ReactNativeViewAttributes":{"base64":"jTIu8+0WGXaG5sUAnk4snA==","id":164},"merge":{"base64":"ZUZMMbLmrATaH8qjfJvZxw==","id":165},"mergeInto":{"base64":"w/YtZ3UTlPK9//FJWaeB4A==","id":166},"mergeHelpers":{"base64":"8gfQOf9dljc6HG3hkGvTCg==","id":167},"Button":{"base64":"h7d2DxT7/3jYgZKR82q5oA==","id":168},"Text":{"base64":"nf+/af+6i8OLxOAav0sWdQ==","id":169},"TextPropTypes":{"base64":"nypKTud0SRxDSClt5ME7Aw==","id":170},"EdgeInsetsPropType":{"base64":"MNiX/4dQfLDNzB+fr5Uo1A==","id":171},"StyleSheetPropType":{"base64":"r4gJvpjQ5ySzOV4r2yEevw==","id":172},"createStrictShapeTypeChecker":{"base64":"JxLWARwylR1t2//G07CwPw==","id":173},"Touchable":{"base64":"nq+AIfZTVrvzsf3AmMS7Tw==","id":174},"BoundingDimensions":{"base64":"RXnL3lw6g1lQozWVormTzA==","id":175},"PooledClass":{"base64":"q5Ue0b2vajSVW4RTbc09LA==","id":176},"Position":{"base64":"UvXgvDhZvF9eJRMLbH6IgQ==","id":177},"TVEventHandler":{"base64":"g9OR3IkU88JU74NHp1zclA==","id":178},"node_modules_fbjs_lib_TouchEventUtils":{"base64":"NHzSYIG9tTQCqwZfQGd93Q==","id":179},"node_modules_fbjs_lib_nullthrows":{"base64":"zhzgyL+7Lrp3yIMcmqrpWQ==","id":180},"TouchableNativeFeedback.android":{"base64":"2qPJY+ddwkE4pdhplswanA==","id":181},"TouchableWithoutFeedback":{"base64":"oRMN033rD2PPujK+GjvueA==","id":182},"node_modules_react-timer-mixin_TimerMixin":{"base64":"KGc7/DrCveNjIs2ic9NQ+w==","id":183},"node_modules_create-react-class_index":{"base64":"CxWhIfQJ3t/VuhQo2v0GFw==","id":184},"node_modules_create-react-class_factory":{"base64":"Xmk4XK3OUkKcV3feKzmt7Q==","id":185},"ensurePositiveDelayProps":{"base64":"8Gworke+sVAB0wXq4XcJjg==","id":186},"ViewAccessibility":{"base64":"wDDxhkd3tpNP2hMwDrXnAw==","id":187},"TouchableOpacity":{"base64":"SQrBYdoV4VDU/N8pbqtGGA==","id":188},"Animated":{"base64":"CiG5W28jD+S/wduaot762Q==","id":189},"AnimatedImplementation":{"base64":"Yq6Fp0YHUIDlER9kGvP9lA==","id":190},"AnimatedEvent":{"base64":"4ZmEZ3mTKMVTUMBVBfvINQ==","id":191},"AnimatedValue":{"base64":"6c0Q1zeJ2clFIgBASz1Itw==","id":192},"AnimatedInterpolation":{"base64":"Gx+tKHo0fUANGUzK9hvDGw==","id":193},"AnimatedNode":{"base64":"1X/w2D4GSYjf1LwVg9nvWQ==","id":194},"NativeAnimatedHelper":{"base64":"Wnd/rvwLyAVe5yYGdH/VAA==","id":195},"AnimatedWithChildren":{"base64":"heRI51bZtmSta8IeyElWbQ==","id":196},"InteractionManager":{"base64":"mbGVIY5+0605K5sfZDSo+Q==","id":197},"TaskQueue":{"base64":"bZbvtwpiLXkkWdKo5PcJ7g==","id":198},"AnimatedAddition":{"base64":"ILDlXLq9igGtuF8Tx1qguA==","id":199},"AnimatedDiffClamp":{"base64":"8reM1KVCXaG9rfhEU0lZhQ==","id":200},"AnimatedDivision":{"base64":"bUoDTjV/WBtNdTuzNnZy8w==","id":201},"AnimatedModulo":{"base64":"LtpgjYmUPu33XFlWfrF3Jw==","id":202},"AnimatedMultiplication":{"base64":"ZlZqGfKBpTux8aBpqNVVzw==","id":203},"AnimatedProps":{"base64":"Xp+UA9ZUQ9ZHAYwL0uwewQ==","id":204},"AnimatedStyle":{"base64":"XXqSYm+fX1U1y9D0sljWpQ==","id":205},"AnimatedTransform":{"base64":"7a1KO3sO3CgYTkO+fwQV/A==","id":206},"AnimatedSubtraction":{"base64":"cB0ocnFcRuM4D7oipEXIuw==","id":207},"AnimatedTracking":{"base64":"AgemUYDwXI+Ok6Y5lfdt4Q==","id":208},"AnimatedValueXY":{"base64":"4vHhY5fTlOAOgXGw4K7H6A==","id":209},"DecayAnimation":{"base64":"oXUFOvqiKKgq0wmvwwdfZg==","id":210},"Animation":{"base64":"1ra2aNvKnU/ndLtlQibr4w==","id":211},"SpringAnimation":{"base64":"ex2Jh5Ztx7NxAS+Fwnadxg==","id":212},"SpringConfig":{"base64":"y4pCGqUBJlmdrNRZhGuxJQ==","id":213},"TimingAnimation":{"base64":"HZTQ1nmLJC4i+H9x6jwYYg==","id":214},"Easing":{"base64":"MkhdUq166iWzvIDUFudqOw==","id":215},"bezier":{"base64":"tPSUGeVAzfxQXwr1L+dSSg==","id":216},"createAnimatedComponent":{"base64":"yJXpS7AMDpKW7RmpeTMxUg==","id":217},"FlatList":{"base64":"rCtyL+9MbjBiHzcuf+bq2g==","id":218},"MetroListView":{"base64":"FaldTyeAMiFQ3Dym59FjBw==","id":219},"ListView":{"base64":"QWxCHnIkKLT24IY/mKJc/w==","id":220},"InternalListViewType":{"base64":"tZXb84eMrZgeDrWemOvCoQ==","id":221},"ListViewDataSource":{"base64":"qUmjkma0vOnuymyzUCqOaw==","id":222},"isEmpty":{"base64":"NxqR5ckeQPYhKrUJlcywzQ==","id":223},"ScrollView":{"base64":"xSebi8P9Jri0K2CXvNe2TQ==","id":224},"ScrollResponder":{"base64":"kwLCR6iqHlwFt2/tASHvdw==","id":225},"FrameRateLogger":{"base64":"hMmHcdQSWqQwcc2PMEOUAg==","id":226},"Keyboard":{"base64":"bOTYWmKKiLvbOsJKjlqcLg==","id":227},"LayoutAnimation":{"base64":"SFXXVcN/zj3GdSb/n6UUsw==","id":228},"dismissKeyboard":{"base64":"QAWouanXaDoGW3i5u0oAAg==","id":229},"Subscribable":{"base64":"rFYdiJ+uVDlZLokkbgebpA==","id":230},"ScrollViewStickyHeader":{"base64":"GzGrd+PV8M995CXTQd/5wA==","id":231},"InternalScrollViewType":{"base64":"dvkL9ytlax8eOXEuQf/SOA==","id":232},"processDecelerationRate":{"base64":"9KjlZZsJUNyn+TYfB7+jqw==","id":233},"StaticRenderer":{"base64":"fl81O7A6cq4BC/gTxvdUwg==","id":234},"node_modules_react-clone-referenced-element_cloneReferencedElement":{"base64":"A79QiZUZDu0wwcDIvPEqTw==","id":235},"RefreshControl":{"base64":"eJutTQof7FBnH8ANNgvhHg==","id":236},"VirtualizedList":{"base64":"tWl8V674OQI0m/tY8nJFNg==","id":237},"Batchinator":{"base64":"bILpHPqcX2JY45lgNhsS0A==","id":238},"FillRateHelper":{"base64":"3N66xv9HHylnLKgw66maWg==","id":239},"ViewabilityHelper":{"base64":"fzh9K9dGFQ4HC+pkJmVWEA==","id":240},"VirtualizeUtils":{"base64":"PXsyhTg6lAlU42gOpJmmBA==","id":241},"Image.android":{"base64":"QIm5Q0AfytzFawNfkTM/NA==","id":242},"ViewPropTypes":{"base64":"5slAz4qsaNSZNQNBDocFlg==","id":243},"PlatformViewPropTypes":{"base64":"V/TooHcEWI8PgNj6nmUGYQ==","id":244},"TVViewPropTypes":{"base64":"NQvU9LAs/OZP3x47ucktGQ==","id":245},"SectionList":{"base64":"vc6YJ2fniI+JFQBzl3aBKQ==","id":246},"VirtualizedSectionList":{"base64":"Fp1v2gVmrvnnbJmlUMKPRg==","id":247},"NativeMethodsMixin":{"base64":"dw4PQCTgXgeZwwa5uFzSdg==","id":248},"CheckBox.android":{"base64":"W5uxBUb1bXL+RmY5yjgtCg==","id":249},"DatePickerIOS.android":{"base64":"wAUtsPOXNV1WV5ibjJp81A==","id":250},"DrawerLayoutAndroid.android":{"base64":"zh1qfuCsXxsMuOB7tpMdxw==","id":251},"StatusBar":{"base64":"+T4dDK/ns7nDT4+slJfoWA==","id":252},"ImageBackground":{"base64":"hG1ra+Qdx5tILEs7zAhZFQ==","id":253},"ensureComponentIsNative":{"base64":"vZDuQd/SCNS+HG6XOvzoyg==","id":254},"ImageEditor":{"base64":"jb9B3umj18vI+SC7qI1kLg==","id":255},"ImageStore":{"base64":"2D6sqsAr7adToKFpmoQJHA==","id":256},"InputAccessoryView":{"base64":"L9r9xGHfoq08iFN4rrG1/w==","id":257},"KeyboardAvoidingView":{"base64":"BVDXiMH52W9B8dG/0kkL4g==","id":258},"MaskedViewIOS.android":{"base64":"cfFjkrosedR+aGWXIyAfmw==","id":259},"UnimplementedView":{"base64":"IBm/IzSXu2/QHY6bVnHUDA==","id":260},"Modal":{"base64":"xZ1t+ALDLwN8KhX/dfrsFw==","id":261},"AppContainer":{"base64":"1VblH9QwkxVwEKL3wNxhbg==","id":262},"I18nManager":{"base64":"57KCFbQFcvNsaZHggMfCYA==","id":263},"NavigatorIOS.android":{"base64":"ijjgOUqlj1lAM9FjTodixA==","id":264},"Picker":{"base64":"5jCLfV9ClQ4aMfA38E58GQ==","id":265},"PickerIOS.android":{"base64":"aMXkHX0yTZYY9tDkNsMA7w==","id":266},"PickerAndroid.android":{"base64":"xbqFWYKuKAm53h6eWz709w==","id":267},"ProgressViewIOS.android":{"base64":"a/9pwCWK3e2LkXKAQ1hTLA==","id":268},"SafeAreaView.android":{"base64":"5/7XpjA8AGEGhVy+PgFZNQ==","id":269},"SegmentedControlIOS.android":{"base64":"sVxKh7d2Z9Ur+93jM3imkw==","id":270},"Slider":{"base64":"LZuadk+wvkvhDhsvzmP1YQ==","id":271},"SnapshotViewIOS.android":{"base64":"IyIOrwha4bQbRQUuK53vcQ==","id":272},"Switch":{"base64":"u8FV+ysRG/YcT1/4kpFeaw==","id":273},"SwitchNativeComponent":{"base64":"UskBspDBPcmp72+kkk2BQg==","id":274},"SwipeableFlatList":{"base64":"wMHhO21mGhMLI/SuV5/+iA==","id":275},"SwipeableRow":{"base64":"gIr8bKZ0vKhT5Dm6HEB4Kg==","id":276},"PanResponder":{"base64":"vxL6NL1PqV7xyqMSIUP2Rg==","id":277},"TouchHistoryMath":{"base64":"cEJQ2/cjgIc9Ti6cP4e91Q==","id":278},"SwipeableListView":{"base64":"8WTNuasOKz4ZvsM0TfWbfw==","id":279},"SwipeableListViewDataSource":{"base64":"VJdD6/UHmJQ725Upz5TRvQ==","id":280},"TabBarIOS.android":{"base64":"CLAdgghx+6CsWRRaQ6U2sA==","id":281},"TabBarItemIOS.android":{"base64":"zyJyKL/78YUzfaDFSYx+Cw==","id":282},"TextInput":{"base64":"yFJ1X4XoC/ohq3VPjd6T3A==","id":283},"DocumentSelectionState":{"base64":"wybxINUS+GVfI5NjC5egZg==","id":284},"mixInEventEmitter":{"base64":"J06gf8aR918LuwWgVzt59w==","id":285},"EventEmitterWithHolding":{"base64":"oEQjV0Khf4OahcvM4tLqpQ==","id":286},"EventHolder":{"base64":"4cd1tBeE45Heby5VzGXN4w==","id":287},"node_modules_fbjs_lib_keyOf":{"base64":"qzmX+i5pw3sOKVnxG8mieQ==","id":288},"ToastAndroid.android":{"base64":"eH5aiUodwMfOMeRyqWJt5g==","id":289},"ToolbarAndroid.android":{"base64":"uFqCZ/b6RT4iLiPCWB+Qnw==","id":290},"TouchableHighlight":{"base64":"Fu7ZLeAtZmMOzlVdhmV5yA==","id":291},"ViewPagerAndroid.android":{"base64":"wltW3CC2MiB7+1qvDUFTmA==","id":292},"WebView.android":{"base64":"s0/JJUzKq9D/q7La11jwew==","id":293},"WebViewShared":{"base64":"4606m00joG8i/a4EJaTsvw==","id":294},"node_modules_escape-string-regexp_index":{"base64":"rusK6YAQe7vXaDpsKjRzXQ==","id":295},"ActionSheetIOS":{"base64":"s3QxpLIgH1lDLiWw0QqzLw==","id":296},"AppRegistry":{"base64":"ZbMhFqtvybRrDRTHF/qa0w==","id":297},"BugReporting":{"base64":"dsVrhQkYdQNqt4278Tp2Iw==","id":298},"dumpReactTree":{"base64":"x3JpZPLjikP5ehxfwyiJ/Q==","id":299},"SceneTracker":{"base64":"7VgsQWG2cPaXnhcW9zitgQ==","id":300},"renderApplication":{"base64":"1xO9qae3WW08ijv0qdhXNw==","id":301},"ReactFabricIndicator":{"base64":"a7xFnMw7as+BBEFCUb/99A==","id":302},"BackHandler.android":{"base64":"NAqWoyRHyNmWQ7KYvjKf8A==","id":303},"ReactFabric":{"base64":"jM3PLDXW3TCXs+/OXrk7sg==","id":304},"ReactFabric-prod":{"base64":"bFrqinx1CZRBdzcUKoEoJg==","id":305},"FabricUIManager":{"base64":"bEGO4Eaetac0czdZ/LVq5A==","id":306},"AppState":{"base64":"bi3CeyHAcguITZxFp/rxwg==","id":307},"AsyncStorage":{"base64":"g3EUCpjjBscQSCrXXabFXQ==","id":308},"BackAndroid":{"base64":"3EfjJa1J7EXQ7M5bXiON+g==","id":309},"CameraRoll":{"base64":"5UIRw3OZHiEgbGKlfAoXNQ==","id":310},"Clipboard":{"base64":"I+Wnt5duQS7OIzzq+CV7wg==","id":311},"DatePickerAndroid.android":{"base64":"HZCHkWW3SYl/H8UAZxFQdA==","id":312},"ImagePickerIOS":{"base64":"i8okefTrAChPJCKm009LnA==","id":313},"Linking":{"base64":"TwkpJ1ZP9+Ud+5lCI3UnKg==","id":314},"NetInfo":{"base64":"HuHD3oDLZ3bzSRgmhelsFg==","id":315},"PushNotificationIOS":{"base64":"Axe5X7xfpocRgzWex03BHg==","id":316},"Settings.android":{"base64":"t9fc/NyIcztRRlD29XoKKQ==","id":317},"Share":{"base64":"WpWkJfdDFKlvE6LxNpkheA==","id":318},"StatusBarIOS.android":{"base64":"XIt2HAshgvDxqUBOeH6UgQ==","id":319},"TimePickerAndroid.android":{"base64":"jsmQMKkIpd74EdMBpDcEog==","id":320},"Vibration":{"base64":"VACWFIogQ5ZQ5fFU+3sRlQ==","id":321},"VibrationIOS.android":{"base64":"3qXnO69PmveqRNgX/BasSw==","id":322},"YellowBox":{"base64":"pXECp/v+xQiifDGS8kat3A==","id":323},"takeSnapshot":{"base64":"PZvwXiWgNQxjE0lWb9utUg==","id":324},"PointPropType":{"base64":"O4iCBxKUmOH6laDkipAeVQ==","id":325},"platformEmptyDefaultExport":{"base64":"DQtGOeZs07Tw8IWgpBlDkg==","id":326},"node_modules_lodash_lodash":{"base64":"j6weT87058rGmsS+/DipJQ==","id":327}}